{
  "main": {
    "id": "c2740de4e5524c8d",
    "type": "split",
    "children": [
      {
        "id": "c2d08ddf0b605626",
        "type": "tabs",
        "children": [
          {
            "id": "2b8efd997adec955",
            "type": "leaf",
            "state": {
              "type": "empty",
              "state": {}
            }
          }
        ]
      }
    ],
    "direction": "vertical"
  },
  "left": {
    "id": "20b6dfa2e12c4b15",
    "type": "split",
    "children": [
      {
        "id": "026666fbb66f93d9",
        "type": "tabs",
        "children": [
          {
            "id": "5675b1d79c0b068e",
            "type": "leaf",
            "state": {
              "type": "file-explorer",
              "state": {
                "sortOrder": "alphabetical"
              }
            }
          },
          {
            "id": "8a5321d23991c733",
            "type": "leaf",
            "state": {
              "type": "search",
              "state": {
                "query": "",
                "matchingCase": false,
                "explainSearch": false,
                "collapseAll": false,
                "extraContext": false,
                "sortOrder": "alphabetical"
              }
            }
          },
          {
            "id": "d6cbde0fa31d562e",
            "type": "leaf",
            "state": {
              "type": "bookmarks",
              "state": {}
            }
          }
        ]
      }
    ],
    "direction": "horizontal",
    "width": 200,
    "collapsed": true
  },
  "right": {
    "id": "e7bed9a189fb8211",
    "type": "split",
    "children": [
      {
        "id": "15adceedd45116c2",
        "type": "tabs",
        "children": [
          {
            "id": "16b5541ade9bce4c",
            "type": "leaf",
            "state": {
              "type": "backlink",
              "state": {
                "collapseAll": false,
                "extraContext": false,
                "sortOrder": "alphabetical",
                "showSearch": false,
                "searchQuery": "",
                "backlinkCollapsed": false,
                "unlinkedCollapsed": true
              }
            }
          },
          {
            "id": "eb9f810634b0519a",
            "type": "leaf",
            "state": {
              "type": "outgoing-link",
              "state": {
                "linksCollapsed": false,
                "unlinkedCollapsed": true
              }
            }
          },
          {
            "id": "a04a44446a454ed7",
            "type": "leaf",
            "state": {
              "type": "tag",
              "state": {
                "sortOrder": "frequency",
                "useHierarchy": true
              }
            }
          },
          {
            "id": "55871a021949cd0f",
            "type": "leaf",
            "state": {
              "type": "outline",
              "state": {}
            }
          }
        ]
      }
    ],
    "direction": "horizontal",
    "width": 300,
    "collapsed": true
  },
  "left-ribbon": {
    "hiddenItems": {
      "switcher:Open quick switcher": false,
      "graph:Open graph view": false,
      "canvas:Create new canvas": false,
      "daily-notes:Open today's daily note": false,
      "templates:Insert template": false,
      "command-palette:Open command palette": false
    }
  },
  "active": "2b8efd997adec955",
  "lastOpenFiles": [
    "2023/11/05.md",
    "birthday_19.png",
    "birthday_18.png",
    "birthday_17.png",
    "birthday_16.png",
    "birthday_15.png",
    "birthday_14.png",
    "birthday_13.png",
    "birthday_12.png",
    "birthday_11.png",
    "birthday_10.png",
    "2023/10/22.md",
    "2023/11",
    "2023/10/4913",
    "aquarium_12.mp4",
    "aquarium_11.mp4",
    "aquarium_9.mp4",
    "aquarium_4.mp4",
    "PXL_20231022_085339793.LS.mp4",
    "PXL_20231022_085301307.LS.mp4",
    "PXL_20231022_084540998.LS.mp4",
    "PXL_20231022_082721782.LS.mp4",
    "2023/10/14.md",
    "2023/10/12.md",
    "2023/10/10.md",
    "2023/10/02.md",
    "2023/10/03.md",
    "third-post.md",
    "sketches.md",
    "second-post.md",
    "markdown-style-guide.md",
    "first-post.md"
  ]
}